wiking/__init__.py
wiking/application.py
wiking/configuration.py
wiking/db.py
wiking/export.py
wiking/handler.py
wiking/mod_python_interface.py
wiking/modules.py
wiking/request.py
wiking/test.py
wiking/util.py
wiking/wsgi_interface.py
wiking/cms/__init__.py
wiking/cms/appl.py
wiking/cms/cms.py
wiking/cms/configuration.py
wiking/cms/crypto.py
wiking/cms/texts.py
wiking/cms/users.py
wiking/dbdefs/__init__.py
wiking/dbdefs/wiking_cms.py
wiking/dbdefs/wiking_db.py
wiking/dbdefs/sql/cms_add_email_label.sql
wiking/dbdefs/sql/cms_add_text_label.sql
wiking/dbdefs/sql/cms_attachments_after_update_trigger.sql
wiking/dbdefs/sql/cms_crypto_change_password.sql
wiking/dbdefs/sql/cms_crypto_cook_passwords.sql
wiking/dbdefs/sql/cms_crypto_copy_key.sql
wiking/dbdefs/sql/cms_crypto_delete_key.sql
wiking/dbdefs/sql/cms_crypto_extract_key.sql
wiking/dbdefs/sql/cms_crypto_insert_key.sql
wiking/dbdefs/sql/cms_crypto_lock_passwords.sql
wiking/dbdefs/sql/cms_crypto_unlock_passwords.sql
wiking/dbdefs/sql/cms_crypto_unlocked_passwords_insert_trigger.sql
wiking/dbdefs/sql/cms_discussions_trigger_before_insert.sql
wiking/dbdefs/sql/cms_f_all_user_roles.sql
wiking/dbdefs/sql/cms_f_insert_or_update_user.sql
wiking/dbdefs/sql/cms_f_role_member.sql
wiking/dbdefs/sql/cms_page_tree_order.sql
wiking/dbdefs/sql/cms_page_tree_published.sql
wiking/dbdefs/sql/cms_pages_update_order.sql
wiking/dbdefs/sql/cms_update_session_history.sql
wiking/dbdefs/sql/expanded_role.sql
wiking/dbdefs/sql/f_update_cached_tables.sql
wiking/dbdefs/sql/f_update_cached_tables_after.sql
wiking/dbdefs/sql/role_sets_cycle_check.sql
wiking/dbdefs/sql/role_sets_trigger_after.sql
wiking/dbdefs/sql/unrelated_roles.sql
wiking/dbdefs/sql/update_user_roles.sql
wiking/resources/newsletter-template.html
wiking/resources/css/default.css
wiking/resources/css/discussion.css
wiking/resources/images/shadow.png
wiking/resources/images/wiking-icons.png
wiking/resources/scripts/discussion.js
wiking/resources/scripts/wiking-cms.js
wiking-2.2.1.dist-info/licenses/COPYING
wiking-2.2.1.dist-info/WHEEL
wiking-2.2.1.dist-info/METADATA
wiking-2.2.1.dist-info/RECORD
