Metadata-Version: 2.4
Name: wiking
Version: 2.2.1
Summary: Wiking — Python web application development framework
Author-email: Tomas Cerha <cerha@truecode.cz>
Requires-Python: >=2.7
Classifier: Programming Language :: Python :: 2.7
Classifier: Programming Language :: Python :: 3.5
Classifier: License :: OSI Approved :: GNU General Public License v2 or later (GPLv2+)
License-File: COPYING
Requires-Dist: lcg-framework[all]
Requires-Dist: pbkdf2
Requires-Dist: dnspython ; extra == "cms"
Provides-Extra: cms
